pygments_style_kit/__init__.py
pygments_style_kit/kitdark.py
pygments_style_kit-1.0.1.dist-info/METADATA
pygments_style_kit-1.0.1.dist-info/WHEEL
pygments_style_kit-1.0.1.dist-info/entry_points.txt
pygments_style_kit-1.0.1.dist-info/top_level.txt
pygments_style_kit-1.0.1.dist-info/RECORD
