Metadata-Version: 2.1
Name: pygments-style-kit
Version: 1.0.1
Summary: UNKNOWN
Home-page: https://gitlab.com/mee02/pygments-style-kit
Maintainer: Jakob Jarebica
Maintainer-email: jakob.jarebica@student.kit.edu
License: UNKNOWN
Platform: UNKNOWN
Requires-Dist: pygments
